distributionsgaussianbinomialbyToheeb/Binomialdistribution_challenge.py
distributionsgaussianbinomialbyToheeb/Gaussiandistribution.py
distributionsgaussianbinomialbyToheeb/Generaldistribution.py
distributionsgaussianbinomialbyToheeb/__init__.py
distributionsgaussianbinomialbyToheeb-1.0.dist-info/METADATA
distributionsgaussianbinomialbyToheeb-1.0.dist-info/WHEEL
distributionsgaussianbinomialbyToheeb-1.0.dist-info/top_level.txt
distributionsgaussianbinomialbyToheeb-1.0.dist-info/RECORD
