Metadata-Version: 2.1
Name: distributionsgaussianbinomialbyToheeb
Version: 1.0
Summary: Gaussian and Binomial distributions
Author: Toheeb B
Requires-Dist: requests
